{
  "properties": {
    "facing": [
      "north",
      "south",
      "west",
      "east"
    ],
    "half": [
      "top",
      "bottom"
    ],
    "open": [
      true,
      true
    ],
    "powered": [
      true,
      true
    ],
    "waterlogged": [
      true,
      true
    ]
  },
  "states": {
    "4145": {
      "facing": "north",
      "half": "top",
      "open": true,
      "powered": true,
      "waterlogged": true
    },
    "4146": {
      "facing": "north",
      "half": "top",
      "open": true,
      "powered": true,
      "waterlogged": true
    },
    "4147": {
      "facing": "north",
      "half": "top",
      "open": true,
      "powered": true,
      "waterlogged": true
    },
    "4148": {
      "facing": "north",
      "half": "top",
      "open": true,
      "powered": true,
      "waterlogged": true
    },
    "4149": {
      "facing": "north",
      "half": "top",
      "open": true,
      "powered": true,
      "waterlogged": true
    },
    "4150": {
      "facing": "north",
      "half": "top",
      "open": true,
      "powered": true,
      "waterlogged": true
    },
    "4151": {
      "facing": "north",
      "half": "top",
      "open": true,
      "powered": true,
      "waterlogged": true
    },
    "4152": {
      "facing": "north",
      "half": "top",
      "open": true,
      "powered": true,
      "waterlogged": true
    },
    "4153": {
      "facing": "north",
      "half": "bottom",
      "open": true,
      "powered": true,
      "waterlogged": true
    },
    "4154": {
      "facing": "north",
      "half": "bottom",
      "open": true,
      "powered": true,
      "waterlogged": true
    },
    "4155": {
      "facing": "north",
      "half": "bottom",
      "open": true,
      "powered": true,
      "waterlogged": true
    },
    "4156": {
      "facing": "north",
      "half": "bottom",
      "open": true,
      "powered": true,
      "waterlogged": true
    },
    "4157": {
      "facing": "north",
      "half": "bottom",
      "open": true,
      "powered": true,
      "waterlogged": true
    },
    "4158": {
      "facing": "north",
      "half": "bottom",
      "open": true,
      "powered": true,
      "waterlogged": true
    },
    "4159": {
      "facing": "north",
      "half": "bottom",
      "open": true,
      "powered": true,
      "waterlogged": true
    },
    "4160": {
      "facing": "north",
      "half": "bottom",
      "open": true,
      "powered": true,
      "waterlogged": true
    },
    "4161": {
      "facing": "south",
      "half": "top",
      "open": true,
      "powered": true,
      "waterlogged": true
    },
    "4162": {
      "facing": "south",
      "half": "top",
      "open": true,
      "powered": true,
      "waterlogged": true
    },
    "4163": {
      "facing": "south",
      "half": "top",
      "open": true,
      "powered": true,
      "waterlogged": true
    },
    "4164": {
      "facing": "south",
      "half": "top",
      "open": true,
      "powered": true,
      "waterlogged": true
    },
    "4165": {
      "facing": "south",
      "half": "top",
      "open": true,
      "powered": true,
      "waterlogged": true
    },
    "4166": {
      "facing": "south",
      "half": "top",
      "open": true,
      "powered": true,
      "waterlogged": true
    },
    "4167": {
      "facing": "south",
      "half": "top",
      "open": true,
      "powered": true,
      "waterlogged": true
    },
    "4168": {
      "facing": "south",
      "half": "top",
      "open": true,
      "powered": true,
      "waterlogged": true
    },
    "4169": {
      "facing": "south",
      "half": "bottom",
      "open": true,
      "powered": true,
      "waterlogged": true
    },
    "4170": {
      "facing": "south",
      "half": "bottom",
      "open": true,
      "powered": true,
      "waterlogged": true
    },
    "4171": {
      "facing": "south",
      "half": "bottom",
      "open": true,
      "powered": true,
      "waterlogged": true
    },
    "4172": {
      "facing": "south",
      "half": "bottom",
      "open": true,
      "powered": true,
      "waterlogged": true
    },
    "4173": {
      "facing": "south",
      "half": "bottom",
      "open": true,
      "powered": true,
      "waterlogged": true
    },
    "4174": {
      "facing": "south",
      "half": "bottom",
      "open": true,
      "powered": true,
      "waterlogged": true
    },
    "4175": {
      "facing": "south",
      "half": "bottom",
      "open": true,
      "powered": true,
      "waterlogged": true
    },
    "4176": {
      "facing": "south",
      "half": "bottom",
      "open": true,
      "powered": true,
      "waterlogged": true
    },
    "4177": {
      "facing": "west",
      "half": "top",
      "open": true,
      "powered": true,
      "waterlogged": true
    },
    "4178": {
      "facing": "west",
      "half": "top",
      "open": true,
      "powered": true,
      "waterlogged": true
    },
    "4179": {
      "facing": "west",
      "half": "top",
      "open": true,
      "powered": true,
      "waterlogged": true
    },
    "4180": {
      "facing": "west",
      "half": "top",
      "open": true,
      "powered": true,
      "waterlogged": true
    },
    "4181": {
      "facing": "west",
      "half": "top",
      "open": true,
      "powered": true,
      "waterlogged": true
    },
    "4182": {
      "facing": "west",
      "half": "top",
      "open": true,
      "powered": true,
      "waterlogged": true
    },
    "4183": {
      "facing": "west",
      "half": "top",
      "open": true,
      "powered": true,
      "waterlogged": true
    },
    "4184": {
      "facing": "west",
      "half": "top",
      "open": true,
      "powered": true,
      "waterlogged": true
    },
    "4185": {
      "facing": "west",
      "half": "bottom",
      "open": true,
      "powered": true,
      "waterlogged": true
    },
    "4186": {
      "facing": "west",
      "half": "bottom",
      "open": true,
      "powered": true,
      "waterlogged": true
    },
    "4187": {
      "facing": "west",
      "half": "bottom",
      "open": true,
      "powered": true,
      "waterlogged": true
    },
    "4188": {
      "facing": "west",
      "half": "bottom",
      "open": true,
      "powered": true,
      "waterlogged": true
    },
    "4189": {
      "facing": "west",
      "half": "bottom",
      "open": true,
      "powered": true,
      "waterlogged": true
    },
    "4190": {
      "facing": "west",
      "half": "bottom",
      "open": true,
      "powered": true,
      "waterlogged": true
    },
    "4191": {
      "facing": "west",
      "half": "bottom",
      "open": true,
      "powered": true,
      "waterlogged": true
    },
    "4192": {
      "facing": "west",
      "half": "bottom",
      "open": true,
      "powered": true,
      "waterlogged": true
    },
    "4193": {
      "facing": "east",
      "half": "top",
      "open": true,
      "powered": true,
      "waterlogged": true
    },
    "4194": {
      "facing": "east",
      "half": "top",
      "open": true,
      "powered": true,
      "waterlogged": true
    },
    "4195": {
      "facing": "east",
      "half": "top",
      "open": true,
      "powered": true,
      "waterlogged": true
    },
    "4196": {
      "facing": "east",
      "half": "top",
      "open": true,
      "powered": true,
      "waterlogged": true
    },
    "4197": {
      "facing": "east",
      "half": "top",
      "open": true,
      "powered": true,
      "waterlogged": true
    },
    "4198": {
      "facing": "east",
      "half": "top",
      "open": true,
      "powered": true,
      "waterlogged": true
    },
    "4199": {
      "facing": "east",
      "half": "top",
      "open": true,
      "powered": true,
      "waterlogged": true
    },
    "4200": {
      "facing": "east",
      "half": "top",
      "open": true,
      "powered": true,
      "waterlogged": true
    },
    "4201": {
      "facing": "east",
      "half": "bottom",
      "open": true,
      "powered": true,
      "waterlogged": true
    },
    "4202": {
      "facing": "east",
      "half": "bottom",
      "open": true,
      "powered": true,
      "waterlogged": true
    },
    "4203": {
      "facing": "east",
      "half": "bottom",
      "open": true,
      "powered": true,
      "waterlogged": true
    },
    "4204": {
      "facing": "east",
      "half": "bottom",
      "open": true,
      "powered": true,
      "waterlogged": true
    },
    "4205": {
      "facing": "east",
      "half": "bottom",
      "open": true,
      "powered": true,
      "waterlogged": true
    },
    "4206": {
      "facing": "east",
      "half": "bottom",
      "open": true,
      "powered": true,
      "waterlogged": true
    },
    "4207": {
      "facing": "east",
      "half": "bottom",
      "open": true,
      "powered": true,
      "waterlogged": true
    },
    "4208": {
      "facing": "east",
      "half": "bottom",
      "open": true,
      "powered": true,
      "waterlogged": true
    },
    "default": 4160
  }
}