{
  "subtitle": "subtitles.block.generic.break",
  "sounds": [
    {
      "name": "block/copper_bulb/break1",
      "hash": "10b623aa5b21f3eebd19b0ad6cc6703c5ac4e9d1",
      "weight": 1,
      "type": "sounds",
      "volume": 1,
      "pitch": 1,
      "attenuation_distance": 16,
      "size": 10497,
      "preload": false,
      "stream": false
    },
    {
      "name": "block/copper_bulb/break2",
      "hash": "43d226ad60714e32737509567d016fd5a675eb57",
      "weight": 1,
      "type": "sounds",
      "volume": 1,
      "pitch": 1,
      "attenuation_distance": 16,
      "size": 10212,
      "preload": false,
      "stream": false
    },
    {
      "name": "block/copper_bulb/break3",
      "hash": "0fec721082e69afd88f9be89e4831e1d266fd2a7",
      "weight": 1,
      "type": "sounds",
      "volume": 1,
      "pitch": 1,
      "attenuation_distance": 16,
      "size": 11117,
      "preload": false,
      "stream": false
    },
    {
      "name": "block/copper_bulb/break4",
      "hash": "826f002c21ee2c9a51ca9280ac3f5bdd855c662d",
      "weight": 1,
      "type": "sounds",
      "volume": 1,
      "pitch": 1,
      "attenuation_distance": 16,
      "size": 9127,
      "preload": false,
      "stream": false
    }
  ]
}