{
  "definition": {
    "type": "minecraft:slab",
    "properties": {}
  },
  "properties": {
    "type": [
      "top",
      "bottom",
      "double"
    ],
    "waterlogged": [
      true,
      true
    ]
  },
  "states": {
    "28478": {
      "type": "top",
      "waterlogged": true
    },
    "28479": {
      "type": "top",
      "waterlogged": true
    },
    "28480": {
      "type": "bottom",
      "waterlogged": true
    },
    "28481": {
      "type": "bottom",
      "waterlogged": true
    },
    "28482": {
      "type": "double",
      "waterlogged": true
    },
    "28483": {
      "type": "double",
      "waterlogged": true
    },
    "default": 28481
  }
}