{
  "definition": {
    "type": "minecraft:trapdoor",
    "block_set_type": "jungle",
    "properties": {}
  },
  "properties": {
    "facing": [
      "north",
      "south",
      "west",
      "east"
    ],
    "half": [
      "top",
      "bottom"
    ],
    "open": [
      true,
      true
    ],
    "powered": [
      true,
      true
    ],
    "waterlogged": [
      true,
      true
    ]
  },
  "states": {
    "6329": {
      "facing": "north",
      "half": "top",
      "open": true,
      "powered": true,
      "waterlogged": true
    },
    "6330": {
      "facing": "north",
      "half": "top",
      "open": true,
      "powered": true,
      "waterlogged": true
    },
    "6331": {
      "facing": "north",
      "half": "top",
      "open": true,
      "powered": true,
      "waterlogged": true
    },
    "6332": {
      "facing": "north",
      "half": "top",
      "open": true,
      "powered": true,
      "waterlogged": true
    },
    "6333": {
      "facing": "north",
      "half": "top",
      "open": true,
      "powered": true,
      "waterlogged": true
    },
    "6334": {
      "facing": "north",
      "half": "top",
      "open": true,
      "powered": true,
      "waterlogged": true
    },
    "6335": {
      "facing": "north",
      "half": "top",
      "open": true,
      "powered": true,
      "waterlogged": true
    },
    "6336": {
      "facing": "north",
      "half": "top",
      "open": true,
      "powered": true,
      "waterlogged": true
    },
    "6337": {
      "facing": "north",
      "half": "bottom",
      "open": true,
      "powered": true,
      "waterlogged": true
    },
    "6338": {
      "facing": "north",
      "half": "bottom",
      "open": true,
      "powered": true,
      "waterlogged": true
    },
    "6339": {
      "facing": "north",
      "half": "bottom",
      "open": true,
      "powered": true,
      "waterlogged": true
    },
    "6340": {
      "facing": "north",
      "half": "bottom",
      "open": true,
      "powered": true,
      "waterlogged": true
    },
    "6341": {
      "facing": "north",
      "half": "bottom",
      "open": true,
      "powered": true,
      "waterlogged": true
    },
    "6342": {
      "facing": "north",
      "half": "bottom",
      "open": true,
      "powered": true,
      "waterlogged": true
    },
    "6343": {
      "facing": "north",
      "half": "bottom",
      "open": true,
      "powered": true,
      "waterlogged": true
    },
    "6344": {
      "facing": "north",
      "half": "bottom",
      "open": true,
      "powered": true,
      "waterlogged": true
    },
    "6345": {
      "facing": "south",
      "half": "top",
      "open": true,
      "powered": true,
      "waterlogged": true
    },
    "6346": {
      "facing": "south",
      "half": "top",
      "open": true,
      "powered": true,
      "waterlogged": true
    },
    "6347": {
      "facing": "south",
      "half": "top",
      "open": true,
      "powered": true,
      "waterlogged": true
    },
    "6348": {
      "facing": "south",
      "half": "top",
      "open": true,
      "powered": true,
      "waterlogged": true
    },
    "6349": {
      "facing": "south",
      "half": "top",
      "open": true,
      "powered": true,
      "waterlogged": true
    },
    "6350": {
      "facing": "south",
      "half": "top",
      "open": true,
      "powered": true,
      "waterlogged": true
    },
    "6351": {
      "facing": "south",
      "half": "top",
      "open": true,
      "powered": true,
      "waterlogged": true
    },
    "6352": {
      "facing": "south",
      "half": "top",
      "open": true,
      "powered": true,
      "waterlogged": true
    },
    "6353": {
      "facing": "south",
      "half": "bottom",
      "open": true,
      "powered": true,
      "waterlogged": true
    },
    "6354": {
      "facing": "south",
      "half": "bottom",
      "open": true,
      "powered": true,
      "waterlogged": true
    },
    "6355": {
      "facing": "south",
      "half": "bottom",
      "open": true,
      "powered": true,
      "waterlogged": true
    },
    "6356": {
      "facing": "south",
      "half": "bottom",
      "open": true,
      "powered": true,
      "waterlogged": true
    },
    "6357": {
      "facing": "south",
      "half": "bottom",
      "open": true,
      "powered": true,
      "waterlogged": true
    },
    "6358": {
      "facing": "south",
      "half": "bottom",
      "open": true,
      "powered": true,
      "waterlogged": true
    },
    "6359": {
      "facing": "south",
      "half": "bottom",
      "open": true,
      "powered": true,
      "waterlogged": true
    },
    "6360": {
      "facing": "south",
      "half": "bottom",
      "open": true,
      "powered": true,
      "waterlogged": true
    },
    "6361": {
      "facing": "west",
      "half": "top",
      "open": true,
      "powered": true,
      "waterlogged": true
    },
    "6362": {
      "facing": "west",
      "half": "top",
      "open": true,
      "powered": true,
      "waterlogged": true
    },
    "6363": {
      "facing": "west",
      "half": "top",
      "open": true,
      "powered": true,
      "waterlogged": true
    },
    "6364": {
      "facing": "west",
      "half": "top",
      "open": true,
      "powered": true,
      "waterlogged": true
    },
    "6365": {
      "facing": "west",
      "half": "top",
      "open": true,
      "powered": true,
      "waterlogged": true
    },
    "6366": {
      "facing": "west",
      "half": "top",
      "open": true,
      "powered": true,
      "waterlogged": true
    },
    "6367": {
      "facing": "west",
      "half": "top",
      "open": true,
      "powered": true,
      "waterlogged": true
    },
    "6368": {
      "facing": "west",
      "half": "top",
      "open": true,
      "powered": true,
      "waterlogged": true
    },
    "6369": {
      "facing": "west",
      "half": "bottom",
      "open": true,
      "powered": true,
      "waterlogged": true
    },
    "6370": {
      "facing": "west",
      "half": "bottom",
      "open": true,
      "powered": true,
      "waterlogged": true
    },
    "6371": {
      "facing": "west",
      "half": "bottom",
      "open": true,
      "powered": true,
      "waterlogged": true
    },
    "6372": {
      "facing": "west",
      "half": "bottom",
      "open": true,
      "powered": true,
      "waterlogged": true
    },
    "6373": {
      "facing": "west",
      "half": "bottom",
      "open": true,
      "powered": true,
      "waterlogged": true
    },
    "6374": {
      "facing": "west",
      "half": "bottom",
      "open": true,
      "powered": true,
      "waterlogged": true
    },
    "6375": {
      "facing": "west",
      "half": "bottom",
      "open": true,
      "powered": true,
      "waterlogged": true
    },
    "6376": {
      "facing": "west",
      "half": "bottom",
      "open": true,
      "powered": true,
      "waterlogged": true
    },
    "6377": {
      "facing": "east",
      "half": "top",
      "open": true,
      "powered": true,
      "waterlogged": true
    },
    "6378": {
      "facing": "east",
      "half": "top",
      "open": true,
      "powered": true,
      "waterlogged": true
    },
    "6379": {
      "facing": "east",
      "half": "top",
      "open": true,
      "powered": true,
      "waterlogged": true
    },
    "6380": {
      "facing": "east",
      "half": "top",
      "open": true,
      "powered": true,
      "waterlogged": true
    },
    "6381": {
      "facing": "east",
      "half": "top",
      "open": true,
      "powered": true,
      "waterlogged": true
    },
    "6382": {
      "facing": "east",
      "half": "top",
      "open": true,
      "powered": true,
      "waterlogged": true
    },
    "6383": {
      "facing": "east",
      "half": "top",
      "open": true,
      "powered": true,
      "waterlogged": true
    },
    "6384": {
      "facing": "east",
      "half": "top",
      "open": true,
      "powered": true,
      "waterlogged": true
    },
    "6385": {
      "facing": "east",
      "half": "bottom",
      "open": true,
      "powered": true,
      "waterlogged": true
    },
    "6386": {
      "facing": "east",
      "half": "bottom",
      "open": true,
      "powered": true,
      "waterlogged": true
    },
    "6387": {
      "facing": "east",
      "half": "bottom",
      "open": true,
      "powered": true,
      "waterlogged": true
    },
    "6388": {
      "facing": "east",
      "half": "bottom",
      "open": true,
      "powered": true,
      "waterlogged": true
    },
    "6389": {
      "facing": "east",
      "half": "bottom",
      "open": true,
      "powered": true,
      "waterlogged": true
    },
    "6390": {
      "facing": "east",
      "half": "bottom",
      "open": true,
      "powered": true,
      "waterlogged": true
    },
    "6391": {
      "facing": "east",
      "half": "bottom",
      "open": true,
      "powered": true,
      "waterlogged": true
    },
    "6392": {
      "facing": "east",
      "half": "bottom",
      "open": true,
      "powered": true,
      "waterlogged": true
    },
    "default": 6344
  }
}