{
  "properties": {
    "east": [
      true,
      true
    ],
    "north": [
      true,
      true
    ],
    "south": [
      true,
      true
    ],
    "up": [
      true,
      true
    ],
    "waterlogged": [
      true,
      true
    ],
    "west": [
      true,
      true
    ]
  },
  "states": {
    "10383": {
      "east": true,
      "north": true,
      "south": true,
      "up": true,
      "waterlogged": true,
      "west": true
    },
    "10384": {
      "east": true,
      "north": true,
      "south": true,
      "up": true,
      "waterlogged": true,
      "west": true
    },
    "10385": {
      "east": true,
      "north": true,
      "south": true,
      "up": true,
      "waterlogged": true,
      "west": true
    },
    "10386": {
      "east": true,
      "north": true,
      "south": true,
      "up": true,
      "waterlogged": true,
      "west": true
    },
    "10387": {
      "east": true,
      "north": true,
      "south": true,
      "up": true,
      "waterlogged": true,
      "west": true
    },
    "10388": {
      "east": true,
      "north": true,
      "south": true,
      "up": true,
      "waterlogged": true,
      "west": true
    },
    "10389": {
      "east": true,
      "north": true,
      "south": true,
      "up": true,
      "waterlogged": true,
      "west": true
    },
    "10390": {
      "east": true,
      "north": true,
      "south": true,
      "up": true,
      "waterlogged": true,
      "west": true
    },
    "10391": {
      "east": true,
      "north": true,
      "south": true,
      "up": true,
      "waterlogged": true,
      "west": true
    },
    "10392": {
      "east": true,
      "north": true,
      "south": true,
      "up": true,
      "waterlogged": true,
      "west": true
    },
    "10393": {
      "east": true,
      "north": true,
      "south": true,
      "up": true,
      "waterlogged": true,
      "west": true
    },
    "10394": {
      "east": true,
      "north": true,
      "south": true,
      "up": true,
      "waterlogged": true,
      "west": true
    },
    "10395": {
      "east": true,
      "north": true,
      "south": true,
      "up": true,
      "waterlogged": true,
      "west": true
    },
    "10396": {
      "east": true,
      "north": true,
      "south": true,
      "up": true,
      "waterlogged": true,
      "west": true
    },
    "10397": {
      "east": true,
      "north": true,
      "south": true,
      "up": true,
      "waterlogged": true,
      "west": true
    },
    "10398": {
      "east": true,
      "north": true,
      "south": true,
      "up": true,
      "waterlogged": true,
      "west": true
    },
    "10399": {
      "east": true,
      "north": true,
      "south": true,
      "up": true,
      "waterlogged": true,
      "west": true
    },
    "10400": {
      "east": true,
      "north": true,
      "south": true,
      "up": true,
      "waterlogged": true,
      "west": true
    },
    "10401": {
      "east": true,
      "north": true,
      "south": true,
      "up": true,
      "waterlogged": true,
      "west": true
    },
    "10402": {
      "east": true,
      "north": true,
      "south": true,
      "up": true,
      "waterlogged": true,
      "west": true
    },
    "10403": {
      "east": true,
      "north": true,
      "south": true,
      "up": true,
      "waterlogged": true,
      "west": true
    },
    "10404": {
      "east": true,
      "north": true,
      "south": true,
      "up": true,
      "waterlogged": true,
      "west": true
    },
    "10405": {
      "east": true,
      "north": true,
      "south": true,
      "up": true,
      "waterlogged": true,
      "west": true
    },
    "10406": {
      "east": true,
      "north": true,
      "south": true,
      "up": true,
      "waterlogged": true,
      "west": true
    },
    "10407": {
      "east": true,
      "north": true,
      "south": true,
      "up": true,
      "waterlogged": true,
      "west": true
    },
    "10408": {
      "east": true,
      "north": true,
      "south": true,
      "up": true,
      "waterlogged": true,
      "west": true
    },
    "10409": {
      "east": true,
      "north": true,
      "south": true,
      "up": true,
      "waterlogged": true,
      "west": true
    },
    "10410": {
      "east": true,
      "north": true,
      "south": true,
      "up": true,
      "waterlogged": true,
      "west": true
    },
    "10411": {
      "east": true,
      "north": true,
      "south": true,
      "up": true,
      "waterlogged": true,
      "west": true
    },
    "10412": {
      "east": true,
      "north": true,
      "south": true,
      "up": true,
      "waterlogged": true,
      "west": true
    },
    "10413": {
      "east": true,
      "north": true,
      "south": true,
      "up": true,
      "waterlogged": true,
      "west": true
    },
    "10414": {
      "east": true,
      "north": true,
      "south": true,
      "up": true,
      "waterlogged": true,
      "west": true
    },
    "10415": {
      "east": true,
      "north": true,
      "south": true,
      "up": true,
      "waterlogged": true,
      "west": true
    },
    "10416": {
      "east": true,
      "north": true,
      "south": true,
      "up": true,
      "waterlogged": true,
      "west": true
    },
    "10417": {
      "east": true,
      "north": true,
      "south": true,
      "up": true,
      "waterlogged": true,
      "west": true
    },
    "10418": {
      "east": true,
      "north": true,
      "south": true,
      "up": true,
      "waterlogged": true,
      "west": true
    },
    "10419": {
      "east": true,
      "north": true,
      "south": true,
      "up": true,
      "waterlogged": true,
      "west": true
    },
    "10420": {
      "east": true,
      "north": true,
      "south": true,
      "up": true,
      "waterlogged": true,
      "west": true
    },
    "10421": {
      "east": true,
      "north": true,
      "south": true,
      "up": true,
      "waterlogged": true,
      "west": true
    },
    "10422": {
      "east": true,
      "north": true,
      "south": true,
      "up": true,
      "waterlogged": true,
      "west": true
    },
    "10423": {
      "east": true,
      "north": true,
      "south": true,
      "up": true,
      "waterlogged": true,
      "west": true
    },
    "10424": {
      "east": true,
      "north": true,
      "south": true,
      "up": true,
      "waterlogged": true,
      "west": true
    },
    "10425": {
      "east": true,
      "north": true,
      "south": true,
      "up": true,
      "waterlogged": true,
      "west": true
    },
    "10426": {
      "east": true,
      "north": true,
      "south": true,
      "up": true,
      "waterlogged": true,
      "west": true
    },
    "10427": {
      "east": true,
      "north": true,
      "south": true,
      "up": true,
      "waterlogged": true,
      "west": true
    },
    "10428": {
      "east": true,
      "north": true,
      "south": true,
      "up": true,
      "waterlogged": true,
      "west": true
    },
    "10429": {
      "east": true,
      "north": true,
      "south": true,
      "up": true,
      "waterlogged": true,
      "west": true
    },
    "10430": {
      "east": true,
      "north": true,
      "south": true,
      "up": true,
      "waterlogged": true,
      "west": true
    },
    "10431": {
      "east": true,
      "north": true,
      "south": true,
      "up": true,
      "waterlogged": true,
      "west": true
    },
    "10432": {
      "east": true,
      "north": true,
      "south": true,
      "up": true,
      "waterlogged": true,
      "west": true
    },
    "10433": {
      "east": true,
      "north": true,
      "south": true,
      "up": true,
      "waterlogged": true,
      "west": true
    },
    "10434": {
      "east": true,
      "north": true,
      "south": true,
      "up": true,
      "waterlogged": true,
      "west": true
    },
    "10435": {
      "east": true,
      "north": true,
      "south": true,
      "up": true,
      "waterlogged": true,
      "west": true
    },
    "10436": {
      "east": true,
      "north": true,
      "south": true,
      "up": true,
      "waterlogged": true,
      "west": true
    },
    "10437": {
      "east": true,
      "north": true,
      "south": true,
      "up": true,
      "waterlogged": true,
      "west": true
    },
    "10438": {
      "east": true,
      "north": true,
      "south": true,
      "up": true,
      "waterlogged": true,
      "west": true
    },
    "10439": {
      "east": true,
      "north": true,
      "south": true,
      "up": true,
      "waterlogged": true,
      "west": true
    },
    "10440": {
      "east": true,
      "north": true,
      "south": true,
      "up": true,
      "waterlogged": true,
      "west": true
    },
    "10441": {
      "east": true,
      "north": true,
      "south": true,
      "up": true,
      "waterlogged": true,
      "west": true
    },
    "10442": {
      "east": true,
      "north": true,
      "south": true,
      "up": true,
      "waterlogged": true,
      "west": true
    },
    "10443": {
      "east": true,
      "north": true,
      "south": true,
      "up": true,
      "waterlogged": true,
      "west": true
    },
    "10444": {
      "east": true,
      "north": true,
      "south": true,
      "up": true,
      "waterlogged": true,
      "west": true
    },
    "10445": {
      "east": true,
      "north": true,
      "south": true,
      "up": true,
      "waterlogged": true,
      "west": true
    },
    "10446": {
      "east": true,
      "north": true,
      "south": true,
      "up": true,
      "waterlogged": true,
      "west": true
    },
    "default": 10442
  }
}