{
  "properties": {
    "pickles": [
      1,
      2,
      3,
      4
    ],
    "waterlogged": [
      true,
      true
    ]
  },
  "states": {
    "12305": {
      "pickles": 1,
      "waterlogged": true
    },
    "12306": {
      "pickles": 1,
      "waterlogged": true
    },
    "12307": {
      "pickles": 2,
      "waterlogged": true
    },
    "12308": {
      "pickles": 2,
      "waterlogged": true
    },
    "12309": {
      "pickles": 3,
      "waterlogged": true
    },
    "12310": {
      "pickles": 3,
      "waterlogged": true
    },
    "12311": {
      "pickles": 4,
      "waterlogged": true
    },
    "12312": {
      "pickles": 4,
      "waterlogged": true
    },
    "default": 12305
  }
}