{
  "definition": {
    "type": "minecraft:stair",
    "base_state": {
      "Name": "minecraft:smooth_quartz"
    },
    "properties": {}
  },
  "properties": {
    "facing": [
      "north",
      "south",
      "west",
      "east"
    ],
    "half": [
      "top",
      "bottom"
    ],
    "shape": [
      "straight",
      "inner_left",
      "inner_right",
      "outer_left",
      "outer_right"
    ],
    "waterlogged": [
      true,
      true
    ]
  },
  "states": {
    "16502": {
      "facing": "north",
      "half": "top",
      "shape": "straight",
      "waterlogged": true
    },
    "16503": {
      "facing": "north",
      "half": "top",
      "shape": "straight",
      "waterlogged": true
    },
    "16504": {
      "facing": "north",
      "half": "top",
      "shape": "inner_left",
      "waterlogged": true
    },
    "16505": {
      "facing": "north",
      "half": "top",
      "shape": "inner_left",
      "waterlogged": true
    },
    "16506": {
      "facing": "north",
      "half": "top",
      "shape": "inner_right",
      "waterlogged": true
    },
    "16507": {
      "facing": "north",
      "half": "top",
      "shape": "inner_right",
      "waterlogged": true
    },
    "16508": {
      "facing": "north",
      "half": "top",
      "shape": "outer_left",
      "waterlogged": true
    },
    "16509": {
      "facing": "north",
      "half": "top",
      "shape": "outer_left",
      "waterlogged": true
    },
    "16510": {
      "facing": "north",
      "half": "top",
      "shape": "outer_right",
      "waterlogged": true
    },
    "16511": {
      "facing": "north",
      "half": "top",
      "shape": "outer_right",
      "waterlogged": true
    },
    "16512": {
      "facing": "north",
      "half": "bottom",
      "shape": "straight",
      "waterlogged": true
    },
    "16513": {
      "facing": "north",
      "half": "bottom",
      "shape": "straight",
      "waterlogged": true
    },
    "16514": {
      "facing": "north",
      "half": "bottom",
      "shape": "inner_left",
      "waterlogged": true
    },
    "16515": {
      "facing": "north",
      "half": "bottom",
      "shape": "inner_left",
      "waterlogged": true
    },
    "16516": {
      "facing": "north",
      "half": "bottom",
      "shape": "inner_right",
      "waterlogged": true
    },
    "16517": {
      "facing": "north",
      "half": "bottom",
      "shape": "inner_right",
      "waterlogged": true
    },
    "16518": {
      "facing": "north",
      "half": "bottom",
      "shape": "outer_left",
      "waterlogged": true
    },
    "16519": {
      "facing": "north",
      "half": "bottom",
      "shape": "outer_left",
      "waterlogged": true
    },
    "16520": {
      "facing": "north",
      "half": "bottom",
      "shape": "outer_right",
      "waterlogged": true
    },
    "16521": {
      "facing": "north",
      "half": "bottom",
      "shape": "outer_right",
      "waterlogged": true
    },
    "16522": {
      "facing": "south",
      "half": "top",
      "shape": "straight",
      "waterlogged": true
    },
    "16523": {
      "facing": "south",
      "half": "top",
      "shape": "straight",
      "waterlogged": true
    },
    "16524": {
      "facing": "south",
      "half": "top",
      "shape": "inner_left",
      "waterlogged": true
    },
    "16525": {
      "facing": "south",
      "half": "top",
      "shape": "inner_left",
      "waterlogged": true
    },
    "16526": {
      "facing": "south",
      "half": "top",
      "shape": "inner_right",
      "waterlogged": true
    },
    "16527": {
      "facing": "south",
      "half": "top",
      "shape": "inner_right",
      "waterlogged": true
    },
    "16528": {
      "facing": "south",
      "half": "top",
      "shape": "outer_left",
      "waterlogged": true
    },
    "16529": {
      "facing": "south",
      "half": "top",
      "shape": "outer_left",
      "waterlogged": true
    },
    "16530": {
      "facing": "south",
      "half": "top",
      "shape": "outer_right",
      "waterlogged": true
    },
    "16531": {
      "facing": "south",
      "half": "top",
      "shape": "outer_right",
      "waterlogged": true
    },
    "16532": {
      "facing": "south",
      "half": "bottom",
      "shape": "straight",
      "waterlogged": true
    },
    "16533": {
      "facing": "south",
      "half": "bottom",
      "shape": "straight",
      "waterlogged": true
    },
    "16534": {
      "facing": "south",
      "half": "bottom",
      "shape": "inner_left",
      "waterlogged": true
    },
    "16535": {
      "facing": "south",
      "half": "bottom",
      "shape": "inner_left",
      "waterlogged": true
    },
    "16536": {
      "facing": "south",
      "half": "bottom",
      "shape": "inner_right",
      "waterlogged": true
    },
    "16537": {
      "facing": "south",
      "half": "bottom",
      "shape": "inner_right",
      "waterlogged": true
    },
    "16538": {
      "facing": "south",
      "half": "bottom",
      "shape": "outer_left",
      "waterlogged": true
    },
    "16539": {
      "facing": "south",
      "half": "bottom",
      "shape": "outer_left",
      "waterlogged": true
    },
    "16540": {
      "facing": "south",
      "half": "bottom",
      "shape": "outer_right",
      "waterlogged": true
    },
    "16541": {
      "facing": "south",
      "half": "bottom",
      "shape": "outer_right",
      "waterlogged": true
    },
    "16542": {
      "facing": "west",
      "half": "top",
      "shape": "straight",
      "waterlogged": true
    },
    "16543": {
      "facing": "west",
      "half": "top",
      "shape": "straight",
      "waterlogged": true
    },
    "16544": {
      "facing": "west",
      "half": "top",
      "shape": "inner_left",
      "waterlogged": true
    },
    "16545": {
      "facing": "west",
      "half": "top",
      "shape": "inner_left",
      "waterlogged": true
    },
    "16546": {
      "facing": "west",
      "half": "top",
      "shape": "inner_right",
      "waterlogged": true
    },
    "16547": {
      "facing": "west",
      "half": "top",
      "shape": "inner_right",
      "waterlogged": true
    },
    "16548": {
      "facing": "west",
      "half": "top",
      "shape": "outer_left",
      "waterlogged": true
    },
    "16549": {
      "facing": "west",
      "half": "top",
      "shape": "outer_left",
      "waterlogged": true
    },
    "16550": {
      "facing": "west",
      "half": "top",
      "shape": "outer_right",
      "waterlogged": true
    },
    "16551": {
      "facing": "west",
      "half": "top",
      "shape": "outer_right",
      "waterlogged": true
    },
    "16552": {
      "facing": "west",
      "half": "bottom",
      "shape": "straight",
      "waterlogged": true
    },
    "16553": {
      "facing": "west",
      "half": "bottom",
      "shape": "straight",
      "waterlogged": true
    },
    "16554": {
      "facing": "west",
      "half": "bottom",
      "shape": "inner_left",
      "waterlogged": true
    },
    "16555": {
      "facing": "west",
      "half": "bottom",
      "shape": "inner_left",
      "waterlogged": true
    },
    "16556": {
      "facing": "west",
      "half": "bottom",
      "shape": "inner_right",
      "waterlogged": true
    },
    "16557": {
      "facing": "west",
      "half": "bottom",
      "shape": "inner_right",
      "waterlogged": true
    },
    "16558": {
      "facing": "west",
      "half": "bottom",
      "shape": "outer_left",
      "waterlogged": true
    },
    "16559": {
      "facing": "west",
      "half": "bottom",
      "shape": "outer_left",
      "waterlogged": true
    },
    "16560": {
      "facing": "west",
      "half": "bottom",
      "shape": "outer_right",
      "waterlogged": true
    },
    "16561": {
      "facing": "west",
      "half": "bottom",
      "shape": "outer_right",
      "waterlogged": true
    },
    "16562": {
      "facing": "east",
      "half": "top",
      "shape": "straight",
      "waterlogged": true
    },
    "16563": {
      "facing": "east",
      "half": "top",
      "shape": "straight",
      "waterlogged": true
    },
    "16564": {
      "facing": "east",
      "half": "top",
      "shape": "inner_left",
      "waterlogged": true
    },
    "16565": {
      "facing": "east",
      "half": "top",
      "shape": "inner_left",
      "waterlogged": true
    },
    "16566": {
      "facing": "east",
      "half": "top",
      "shape": "inner_right",
      "waterlogged": true
    },
    "16567": {
      "facing": "east",
      "half": "top",
      "shape": "inner_right",
      "waterlogged": true
    },
    "16568": {
      "facing": "east",
      "half": "top",
      "shape": "outer_left",
      "waterlogged": true
    },
    "16569": {
      "facing": "east",
      "half": "top",
      "shape": "outer_left",
      "waterlogged": true
    },
    "16570": {
      "facing": "east",
      "half": "top",
      "shape": "outer_right",
      "waterlogged": true
    },
    "16571": {
      "facing": "east",
      "half": "top",
      "shape": "outer_right",
      "waterlogged": true
    },
    "16572": {
      "facing": "east",
      "half": "bottom",
      "shape": "straight",
      "waterlogged": true
    },
    "16573": {
      "facing": "east",
      "half": "bottom",
      "shape": "straight",
      "waterlogged": true
    },
    "16574": {
      "facing": "east",
      "half": "bottom",
      "shape": "inner_left",
      "waterlogged": true
    },
    "16575": {
      "facing": "east",
      "half": "bottom",
      "shape": "inner_left",
      "waterlogged": true
    },
    "16576": {
      "facing": "east",
      "half": "bottom",
      "shape": "inner_right",
      "waterlogged": true
    },
    "16577": {
      "facing": "east",
      "half": "bottom",
      "shape": "inner_right",
      "waterlogged": true
    },
    "16578": {
      "facing": "east",
      "half": "bottom",
      "shape": "outer_left",
      "waterlogged": true
    },
    "16579": {
      "facing": "east",
      "half": "bottom",
      "shape": "outer_left",
      "waterlogged": true
    },
    "16580": {
      "facing": "east",
      "half": "bottom",
      "shape": "outer_right",
      "waterlogged": true
    },
    "16581": {
      "facing": "east",
      "half": "bottom",
      "shape": "outer_right",
      "waterlogged": true
    },
    "default": 16513
  }
}