{
  "definition": {
    "type": "minecraft:sulfur_spike",
    "block_to_grow_on": {
      "Name": "minecraft:sulfur"
    },
    "properties": {}
  },
  "properties": {
    "thickness": [
      "tip_merge",
      "tip",
      "frustum",
      "middle",
      "base"
    ],
    "vertical_direction": [
      "up",
      "down"
    ],
    "waterlogged": [
      true,
      true
    ]
  },
  "states": {
    "32194": {
      "thickness": "tip_merge",
      "vertical_direction": "up",
      "waterlogged": true
    },
    "32195": {
      "thickness": "tip_merge",
      "vertical_direction": "up",
      "waterlogged": true
    },
    "32196": {
      "thickness": "tip_merge",
      "vertical_direction": "down",
      "waterlogged": true
    },
    "32197": {
      "thickness": "tip_merge",
      "vertical_direction": "down",
      "waterlogged": true
    },
    "32198": {
      "thickness": "tip",
      "vertical_direction": "up",
      "waterlogged": true
    },
    "32199": {
      "thickness": "tip",
      "vertical_direction": "up",
      "waterlogged": true
    },
    "32200": {
      "thickness": "tip",
      "vertical_direction": "down",
      "waterlogged": true
    },
    "32201": {
      "thickness": "tip",
      "vertical_direction": "down",
      "waterlogged": true
    },
    "32202": {
      "thickness": "frustum",
      "vertical_direction": "up",
      "waterlogged": true
    },
    "32203": {
      "thickness": "frustum",
      "vertical_direction": "up",
      "waterlogged": true
    },
    "32204": {
      "thickness": "frustum",
      "vertical_direction": "down",
      "waterlogged": true
    },
    "32205": {
      "thickness": "frustum",
      "vertical_direction": "down",
      "waterlogged": true
    },
    "32206": {
      "thickness": "middle",
      "vertical_direction": "up",
      "waterlogged": true
    },
    "32207": {
      "thickness": "middle",
      "vertical_direction": "up",
      "waterlogged": true
    },
    "32208": {
      "thickness": "middle",
      "vertical_direction": "down",
      "waterlogged": true
    },
    "32209": {
      "thickness": "middle",
      "vertical_direction": "down",
      "waterlogged": true
    },
    "32210": {
      "thickness": "base",
      "vertical_direction": "up",
      "waterlogged": true
    },
    "32211": {
      "thickness": "base",
      "vertical_direction": "up",
      "waterlogged": true
    },
    "32212": {
      "thickness": "base",
      "vertical_direction": "down",
      "waterlogged": true
    },
    "32213": {
      "thickness": "base",
      "vertical_direction": "down",
      "waterlogged": true
    },
    "default": 32199
  }
}