{
  "definition": {
    "type": "minecraft:vault",
    "properties": {}
  },
  "properties": {
    "facing": [
      "north",
      "south",
      "west",
      "east"
    ],
    "ominous": [
      true,
      true
    ],
    "vault_state": [
      "inactive",
      "active",
      "unlocking",
      "ejecting"
    ]
  },
  "states": {
    "27742": {
      "facing": "north",
      "ominous": true,
      "vault_state": "inactive"
    },
    "27743": {
      "facing": "north",
      "ominous": true,
      "vault_state": "active"
    },
    "27744": {
      "facing": "north",
      "ominous": true,
      "vault_state": "unlocking"
    },
    "27745": {
      "facing": "north",
      "ominous": true,
      "vault_state": "ejecting"
    },
    "27746": {
      "facing": "north",
      "ominous": true,
      "vault_state": "inactive"
    },
    "27747": {
      "facing": "north",
      "ominous": true,
      "vault_state": "active"
    },
    "27748": {
      "facing": "north",
      "ominous": true,
      "vault_state": "unlocking"
    },
    "27749": {
      "facing": "north",
      "ominous": true,
      "vault_state": "ejecting"
    },
    "27750": {
      "facing": "south",
      "ominous": true,
      "vault_state": "inactive"
    },
    "27751": {
      "facing": "south",
      "ominous": true,
      "vault_state": "active"
    },
    "27752": {
      "facing": "south",
      "ominous": true,
      "vault_state": "unlocking"
    },
    "27753": {
      "facing": "south",
      "ominous": true,
      "vault_state": "ejecting"
    },
    "27754": {
      "facing": "south",
      "ominous": true,
      "vault_state": "inactive"
    },
    "27755": {
      "facing": "south",
      "ominous": true,
      "vault_state": "active"
    },
    "27756": {
      "facing": "south",
      "ominous": true,
      "vault_state": "unlocking"
    },
    "27757": {
      "facing": "south",
      "ominous": true,
      "vault_state": "ejecting"
    },
    "27758": {
      "facing": "west",
      "ominous": true,
      "vault_state": "inactive"
    },
    "27759": {
      "facing": "west",
      "ominous": true,
      "vault_state": "active"
    },
    "27760": {
      "facing": "west",
      "ominous": true,
      "vault_state": "unlocking"
    },
    "27761": {
      "facing": "west",
      "ominous": true,
      "vault_state": "ejecting"
    },
    "27762": {
      "facing": "west",
      "ominous": true,
      "vault_state": "inactive"
    },
    "27763": {
      "facing": "west",
      "ominous": true,
      "vault_state": "active"
    },
    "27764": {
      "facing": "west",
      "ominous": true,
      "vault_state": "unlocking"
    },
    "27765": {
      "facing": "west",
      "ominous": true,
      "vault_state": "ejecting"
    },
    "27766": {
      "facing": "east",
      "ominous": true,
      "vault_state": "inactive"
    },
    "27767": {
      "facing": "east",
      "ominous": true,
      "vault_state": "active"
    },
    "27768": {
      "facing": "east",
      "ominous": true,
      "vault_state": "unlocking"
    },
    "27769": {
      "facing": "east",
      "ominous": true,
      "vault_state": "ejecting"
    },
    "27770": {
      "facing": "east",
      "ominous": true,
      "vault_state": "inactive"
    },
    "27771": {
      "facing": "east",
      "ominous": true,
      "vault_state": "active"
    },
    "27772": {
      "facing": "east",
      "ominous": true,
      "vault_state": "unlocking"
    },
    "27773": {
      "facing": "east",
      "ominous": true,
      "vault_state": "ejecting"
    },
    "default": 27746
  }
}