{
  "definition": {
    "type": "minecraft:lightning_rod",
    "properties": {}
  },
  "properties": {
    "facing": [
      "north",
      "east",
      "south",
      "west",
      "up",
      "down"
    ],
    "powered": [
      true,
      true
    ],
    "waterlogged": [
      true,
      true
    ]
  },
  "states": {
    "30184": {
      "facing": "north",
      "powered": true,
      "waterlogged": true
    },
    "30185": {
      "facing": "north",
      "powered": true,
      "waterlogged": true
    },
    "30186": {
      "facing": "north",
      "powered": true,
      "waterlogged": true
    },
    "30187": {
      "facing": "north",
      "powered": true,
      "waterlogged": true
    },
    "30188": {
      "facing": "east",
      "powered": true,
      "waterlogged": true
    },
    "30189": {
      "facing": "east",
      "powered": true,
      "waterlogged": true
    },
    "30190": {
      "facing": "east",
      "powered": true,
      "waterlogged": true
    },
    "30191": {
      "facing": "east",
      "powered": true,
      "waterlogged": true
    },
    "30192": {
      "facing": "south",
      "powered": true,
      "waterlogged": true
    },
    "30193": {
      "facing": "south",
      "powered": true,
      "waterlogged": true
    },
    "30194": {
      "facing": "south",
      "powered": true,
      "waterlogged": true
    },
    "30195": {
      "facing": "south",
      "powered": true,
      "waterlogged": true
    },
    "30196": {
      "facing": "west",
      "powered": true,
      "waterlogged": true
    },
    "30197": {
      "facing": "west",
      "powered": true,
      "waterlogged": true
    },
    "30198": {
      "facing": "west",
      "powered": true,
      "waterlogged": true
    },
    "30199": {
      "facing": "west",
      "powered": true,
      "waterlogged": true
    },
    "30200": {
      "facing": "up",
      "powered": true,
      "waterlogged": true
    },
    "30201": {
      "facing": "up",
      "powered": true,
      "waterlogged": true
    },
    "30202": {
      "facing": "up",
      "powered": true,
      "waterlogged": true
    },
    "30203": {
      "facing": "up",
      "powered": true,
      "waterlogged": true
    },
    "30204": {
      "facing": "down",
      "powered": true,
      "waterlogged": true
    },
    "30205": {
      "facing": "down",
      "powered": true,
      "waterlogged": true
    },
    "30206": {
      "facing": "down",
      "powered": true,
      "waterlogged": true
    },
    "30207": {
      "facing": "down",
      "powered": true,
      "waterlogged": true
    },
    "default": 30203
  }
}