{
  "definition": {
    "type": "minecraft:trapdoor",
    "block_set_type": "jungle",
    "properties": {}
  },
  "properties": {
    "facing": [
      "north",
      "south",
      "west",
      "east"
    ],
    "half": [
      "top",
      "bottom"
    ],
    "open": [
      true,
      true
    ],
    "powered": [
      true,
      true
    ],
    "waterlogged": [
      true,
      true
    ]
  },
  "states": {
    "7873": {
      "facing": "north",
      "half": "top",
      "open": true,
      "powered": true,
      "waterlogged": true
    },
    "7874": {
      "facing": "north",
      "half": "top",
      "open": true,
      "powered": true,
      "waterlogged": true
    },
    "7875": {
      "facing": "north",
      "half": "top",
      "open": true,
      "powered": true,
      "waterlogged": true
    },
    "7876": {
      "facing": "north",
      "half": "top",
      "open": true,
      "powered": true,
      "waterlogged": true
    },
    "7877": {
      "facing": "north",
      "half": "top",
      "open": true,
      "powered": true,
      "waterlogged": true
    },
    "7878": {
      "facing": "north",
      "half": "top",
      "open": true,
      "powered": true,
      "waterlogged": true
    },
    "7879": {
      "facing": "north",
      "half": "top",
      "open": true,
      "powered": true,
      "waterlogged": true
    },
    "7880": {
      "facing": "north",
      "half": "top",
      "open": true,
      "powered": true,
      "waterlogged": true
    },
    "7881": {
      "facing": "north",
      "half": "bottom",
      "open": true,
      "powered": true,
      "waterlogged": true
    },
    "7882": {
      "facing": "north",
      "half": "bottom",
      "open": true,
      "powered": true,
      "waterlogged": true
    },
    "7883": {
      "facing": "north",
      "half": "bottom",
      "open": true,
      "powered": true,
      "waterlogged": true
    },
    "7884": {
      "facing": "north",
      "half": "bottom",
      "open": true,
      "powered": true,
      "waterlogged": true
    },
    "7885": {
      "facing": "north",
      "half": "bottom",
      "open": true,
      "powered": true,
      "waterlogged": true
    },
    "7886": {
      "facing": "north",
      "half": "bottom",
      "open": true,
      "powered": true,
      "waterlogged": true
    },
    "7887": {
      "facing": "north",
      "half": "bottom",
      "open": true,
      "powered": true,
      "waterlogged": true
    },
    "7888": {
      "facing": "north",
      "half": "bottom",
      "open": true,
      "powered": true,
      "waterlogged": true
    },
    "7889": {
      "facing": "south",
      "half": "top",
      "open": true,
      "powered": true,
      "waterlogged": true
    },
    "7890": {
      "facing": "south",
      "half": "top",
      "open": true,
      "powered": true,
      "waterlogged": true
    },
    "7891": {
      "facing": "south",
      "half": "top",
      "open": true,
      "powered": true,
      "waterlogged": true
    },
    "7892": {
      "facing": "south",
      "half": "top",
      "open": true,
      "powered": true,
      "waterlogged": true
    },
    "7893": {
      "facing": "south",
      "half": "top",
      "open": true,
      "powered": true,
      "waterlogged": true
    },
    "7894": {
      "facing": "south",
      "half": "top",
      "open": true,
      "powered": true,
      "waterlogged": true
    },
    "7895": {
      "facing": "south",
      "half": "top",
      "open": true,
      "powered": true,
      "waterlogged": true
    },
    "7896": {
      "facing": "south",
      "half": "top",
      "open": true,
      "powered": true,
      "waterlogged": true
    },
    "7897": {
      "facing": "south",
      "half": "bottom",
      "open": true,
      "powered": true,
      "waterlogged": true
    },
    "7898": {
      "facing": "south",
      "half": "bottom",
      "open": true,
      "powered": true,
      "waterlogged": true
    },
    "7899": {
      "facing": "south",
      "half": "bottom",
      "open": true,
      "powered": true,
      "waterlogged": true
    },
    "7900": {
      "facing": "south",
      "half": "bottom",
      "open": true,
      "powered": true,
      "waterlogged": true
    },
    "7901": {
      "facing": "south",
      "half": "bottom",
      "open": true,
      "powered": true,
      "waterlogged": true
    },
    "7902": {
      "facing": "south",
      "half": "bottom",
      "open": true,
      "powered": true,
      "waterlogged": true
    },
    "7903": {
      "facing": "south",
      "half": "bottom",
      "open": true,
      "powered": true,
      "waterlogged": true
    },
    "7904": {
      "facing": "south",
      "half": "bottom",
      "open": true,
      "powered": true,
      "waterlogged": true
    },
    "7905": {
      "facing": "west",
      "half": "top",
      "open": true,
      "powered": true,
      "waterlogged": true
    },
    "7906": {
      "facing": "west",
      "half": "top",
      "open": true,
      "powered": true,
      "waterlogged": true
    },
    "7907": {
      "facing": "west",
      "half": "top",
      "open": true,
      "powered": true,
      "waterlogged": true
    },
    "7908": {
      "facing": "west",
      "half": "top",
      "open": true,
      "powered": true,
      "waterlogged": true
    },
    "7909": {
      "facing": "west",
      "half": "top",
      "open": true,
      "powered": true,
      "waterlogged": true
    },
    "7910": {
      "facing": "west",
      "half": "top",
      "open": true,
      "powered": true,
      "waterlogged": true
    },
    "7911": {
      "facing": "west",
      "half": "top",
      "open": true,
      "powered": true,
      "waterlogged": true
    },
    "7912": {
      "facing": "west",
      "half": "top",
      "open": true,
      "powered": true,
      "waterlogged": true
    },
    "7913": {
      "facing": "west",
      "half": "bottom",
      "open": true,
      "powered": true,
      "waterlogged": true
    },
    "7914": {
      "facing": "west",
      "half": "bottom",
      "open": true,
      "powered": true,
      "waterlogged": true
    },
    "7915": {
      "facing": "west",
      "half": "bottom",
      "open": true,
      "powered": true,
      "waterlogged": true
    },
    "7916": {
      "facing": "west",
      "half": "bottom",
      "open": true,
      "powered": true,
      "waterlogged": true
    },
    "7917": {
      "facing": "west",
      "half": "bottom",
      "open": true,
      "powered": true,
      "waterlogged": true
    },
    "7918": {
      "facing": "west",
      "half": "bottom",
      "open": true,
      "powered": true,
      "waterlogged": true
    },
    "7919": {
      "facing": "west",
      "half": "bottom",
      "open": true,
      "powered": true,
      "waterlogged": true
    },
    "7920": {
      "facing": "west",
      "half": "bottom",
      "open": true,
      "powered": true,
      "waterlogged": true
    },
    "7921": {
      "facing": "east",
      "half": "top",
      "open": true,
      "powered": true,
      "waterlogged": true
    },
    "7922": {
      "facing": "east",
      "half": "top",
      "open": true,
      "powered": true,
      "waterlogged": true
    },
    "7923": {
      "facing": "east",
      "half": "top",
      "open": true,
      "powered": true,
      "waterlogged": true
    },
    "7924": {
      "facing": "east",
      "half": "top",
      "open": true,
      "powered": true,
      "waterlogged": true
    },
    "7925": {
      "facing": "east",
      "half": "top",
      "open": true,
      "powered": true,
      "waterlogged": true
    },
    "7926": {
      "facing": "east",
      "half": "top",
      "open": true,
      "powered": true,
      "waterlogged": true
    },
    "7927": {
      "facing": "east",
      "half": "top",
      "open": true,
      "powered": true,
      "waterlogged": true
    },
    "7928": {
      "facing": "east",
      "half": "top",
      "open": true,
      "powered": true,
      "waterlogged": true
    },
    "7929": {
      "facing": "east",
      "half": "bottom",
      "open": true,
      "powered": true,
      "waterlogged": true
    },
    "7930": {
      "facing": "east",
      "half": "bottom",
      "open": true,
      "powered": true,
      "waterlogged": true
    },
    "7931": {
      "facing": "east",
      "half": "bottom",
      "open": true,
      "powered": true,
      "waterlogged": true
    },
    "7932": {
      "facing": "east",
      "half": "bottom",
      "open": true,
      "powered": true,
      "waterlogged": true
    },
    "7933": {
      "facing": "east",
      "half": "bottom",
      "open": true,
      "powered": true,
      "waterlogged": true
    },
    "7934": {
      "facing": "east",
      "half": "bottom",
      "open": true,
      "powered": true,
      "waterlogged": true
    },
    "7935": {
      "facing": "east",
      "half": "bottom",
      "open": true,
      "powered": true,
      "waterlogged": true
    },
    "7936": {
      "facing": "east",
      "half": "bottom",
      "open": true,
      "powered": true,
      "waterlogged": true
    },
    "default": 7888
  }
}