{
  "subtitle": "subtitles.entity.illusioner.ambient",
  "sounds": [
    {
      "name": "mob/illusion_illager/idle1",
      "hash": "1129d5a7e5217528ee729b69731883961e0e2cdc",
      "weight": 1,
      "type": "sounds",
      "volume": 1,
      "pitch": 1,
      "attenuation_distance": 16,
      "size": 10281,
      "preload": false,
      "stream": false
    },
    {
      "name": "mob/illusion_illager/idle2",
      "hash": "6a2e2114bac7a548fe93c64b271359a544982790",
      "weight": 1,
      "type": "sounds",
      "volume": 1,
      "pitch": 1,
      "attenuation_distance": 16,
      "size": 7856,
      "preload": false,
      "stream": false
    },
    {
      "name": "mob/illusion_illager/idle3",
      "hash": "10cd356e9bffb033e0b92aa9a30da5e6226e4f33",
      "weight": 1,
      "type": "sounds",
      "volume": 1,
      "pitch": 1,
      "attenuation_distance": 16,
      "size": 8398,
      "preload": false,
      "stream": false
    },
    {
      "name": "mob/illusion_illager/idle4",
      "hash": "9aece538dc171535f71a00507384ffddedc14092",
      "weight": 1,
      "type": "sounds",
      "volume": 1,
      "pitch": 1,
      "attenuation_distance": 16,
      "size": 11130,
      "preload": false,
      "stream": false
    }
  ]
}