{
  "properties": {
    "age": [
      0,
      1,
      2,
      3,
      4,
      5,
      6,
      7,
      8,
      9,
      10,
      11,
      12,
      13,
      14,
      15
    ]
  },
  "states": {
    "5633": {
      "age": 0
    },
    "5634": {
      "age": 1
    },
    "5635": {
      "age": 2
    },
    "5636": {
      "age": 3
    },
    "5637": {
      "age": 4
    },
    "5638": {
      "age": 5
    },
    "5639": {
      "age": 6
    },
    "5640": {
      "age": 7
    },
    "5641": {
      "age": 8
    },
    "5642": {
      "age": 9
    },
    "5643": {
      "age": 10
    },
    "5644": {
      "age": 11
    },
    "5645": {
      "age": 12
    },
    "5646": {
      "age": 13
    },
    "5647": {
      "age": 14
    },
    "5648": {
      "age": 15
    },
    "default": 5633
  }
}